couleuvre/.DS_Store
couleuvre/__init__.py
couleuvre/__main__.py
couleuvre/ast/__init__.py
couleuvre/ast/environment.py
couleuvre/ast/nodes.py
couleuvre/ast/parser.py
couleuvre/ast/visitor.py
couleuvre/ast/vyper_wrapper.py
couleuvre/features/__init__.py
couleuvre/features/completion.py
couleuvre/features/definition.py
couleuvre/features/diagnostics.py
couleuvre/features/references.py
couleuvre/features/resolve.py
couleuvre/features/symbol_table.py
couleuvre/features/symbols.py
couleuvre/logger_setup.py
couleuvre/parser.py
couleuvre/server.py
couleuvre/utils.py
couleuvre-0.0.4.dist-info/WHEEL
couleuvre-0.0.4.dist-info/entry_points.txt
couleuvre-0.0.4.dist-info/METADATA
couleuvre-0.0.4.dist-info/RECORD
