Metadata-Version: 2.3
Name: couleuvre
Version: 0.0.4
Summary: Vyper Language Server
Keywords: vyper,language-server,lsp
Author: trocher
Author-email: trocher <tanguy.rocher@chainsecurity.com>
License: MIT License
Requires-Dist: lsprotocol>=2025.0.0
Requires-Dist: pygls>=2.0.0
Requires-Dist: uv>=0.9.17
Requires-Python: >=3.10
